letterchains/__init__.py
letterchains/main.py
letterchains/test_main.py
letterchains-0.1.1.dist-info/entry_points.txt
letterchains-0.1.1.dist-info/WHEEL
letterchains-0.1.1.dist-info/METADATA
letterchains-0.1.1.dist-info/RECORD
